[
  {
    "name": "November 2023-12",
    "size": "3",
    "qp": "https://drive.google.com/file/d/1Ax6YRsAw1Z4O9vv6f-lAEqi9siL1we74/view?usp=sharing",
    "ms": "https://drive.google.com/file/d/1s3PAWkfmzP2N-fuqekuXBgNbQ2Gciy5Y/view?usp=sharing",
    "text1": "View Question Paper",
    "text2": "View Mark Scheme",
    "id": "november_2023_12"
  },
  {
    "name": "November 2023-13",
    "size": "3",
    "qp": "https://drive.google.com/file/d/10lCJT3X18vJFXPk68OE4JZaysJn2q4gM/view?usp=sharing",
    "ms": "https://drive.google.com/file/d/1B7cqF8FtPhR-6Mhlf3R8kZniZqMUegy5/view?usp=sharing",
    "text1": "View Question Paper",
    "text2": "View Mark Scheme",
    "id": "november_2023_13"
  },
  {
    "name": "November 2023-22",
    "size": "3",
    "qp": "https://drive.google.com/file/d/10sYGLSvZx48r2oi2kIPQjkUcXjX9OiiZ/view?usp=sharing",
    "ms": "https://drive.google.com/file/d/1ppzwumrgxl4mehID5BK-c24F7-Jl7UlY/view?usp=sharing",
    "text1": "View Question Paper",
    "text2": "View Mark Scheme",
    "id": "november_2023_22"
  },
  {
    "name": "November 2023-23",
    "size": "3",
    "qp": "https://drive.google.com/file/d/1e8LBF7HUUTeilqKHqb7IRXL6-jg3dVS9/view?usp=sharing",
    "ms": "https://drive.google.com/file/d/1fiNB6eOAwqYFwb822UolhNKYOfV-_qBZ/view?usp=sharing",
    "text1": "View Question Paper",
    "text2": "View Mark Scheme",
    "id": "november_2023_23"
  }
]